gpttsrt/__init__.py
gpttsrt/cmd.py
gpttsrt/constants.py
gpttsrt/gpt_translate.py
gpttsrt/gpttsrt.py
gpttsrt/log.py
gpttsrt-0.0.2.dist-info/LICENSE
gpttsrt-0.0.2.dist-info/METADATA
gpttsrt-0.0.2.dist-info/WHEEL
gpttsrt-0.0.2.dist-info/entry_points.txt
gpttsrt-0.0.2.dist-info/top_level.txt
gpttsrt-0.0.2.dist-info/RECORD
