Metadata-Version: 2.1
Name: gpttsrt
Version: 0.0.2
Summary: Gpt powered subtitle translation tool.
Home-page: https://github.com/Seeker0472/gpttsrt
Author: Seeker472
Author-email: gmx472@qq.com
License-File: LICENSE
Requires-Dist: pysrt ~=1.1.2
Requires-Dist: requests
Requires-Dist: tqdm ~=4.65.0
Requires-Dist: configargparse ~=1.4
Requires-Dist: openai ~=1.9.0
